puslib/__init__.py
puslib/crc_ccitt.py
puslib/exceptions.py
puslib/ident.py
puslib/packet.py
puslib/parameter.py
puslib/process.py
puslib/time.py
puslib/services/__init__.py
puslib/services/error_codes.py
puslib/services/param_report.py
puslib/services/pus_001_request_verification.py
puslib/services/pus_003_housekeeping.py
puslib/services/pus_005_event_reporting.py
puslib/services/pus_008_function_management.py
puslib/services/pus_017_test.py
puslib/services/pus_020_parameter_management.py
puslib/services/service.py
puslib/streams/__init__.py
puslib/streams/buffer.py
puslib/streams/console.py
puslib/streams/file.py
puslib/streams/stream.py
puslib-0.2.5.dist-info/LICENSE
puslib-0.2.5.dist-info/METADATA
puslib-0.2.5.dist-info/WHEEL
puslib-0.2.5.dist-info/top_level.txt
puslib-0.2.5.dist-info/RECORD
