Metadata-Version: 2.1
Name: puslib
Version: 0.2.5
Summary: An implementation of the telemetry and telecommand packet utilization standard (PUS).
Home-page: https://github.com/pxntus/puslib
Author: Pontus Nyman
Author-email: pontusnyman@gmail.com
License: MIT License
Project-URL: Issue Tracker, https://github.com/pxntus/puslib/issues
Classifier: Development Status :: 4 - Beta
Classifier: Intended Audience :: Developers
Classifier: License :: OSI Approved :: MIT License
Classifier: Natural Language :: English
Classifier: Operating System :: OS Independent
Classifier: Programming Language :: Python :: 3
Classifier: Programming Language :: Python :: 3 :: Only
Classifier: Programming Language :: Python :: 3.7
Classifier: Programming Language :: Python :: 3.8
Classifier: Programming Language :: Python :: 3.9
Classifier: Programming Language :: Python :: 3.10
Classifier: Programming Language :: Python :: 3.11
Classifier: Topic :: Communications
Classifier: Topic :: Scientific/Engineering
Requires-Python: >=3.7
License-File: LICENSE
Requires-Dist: bitstring
